scyllapy-1.3.3.dist-info/METADATA
scyllapy-1.3.3.dist-info/WHEEL
scyllapy-1.3.3.dist-info/licenses/LICENSE
scyllapy/exceptions.py
scyllapy/extra_types.py
scyllapy/load_balancing.py
scyllapy/py.typed
scyllapy/query_builder.py
scyllapy/_internal/exceptions.pyi
scyllapy/_internal/extra_types.pyi
scyllapy/_internal/load_balancing.pyi
scyllapy/_internal/query_builder.pyi
scyllapy/_internal/__init__.pyi
scyllapy/__init__.py
scyllapy/_internal.pyd
scyllapy-1.3.3.dist-info/RECORD
